rai_agent_functions_api/__init__.py
rai_agent_functions_api/_client.py
rai_agent_functions_api/_configuration.py
rai_agent_functions_api/_patch.py
rai_agent_functions_api/py.typed
rai_agent_functions_api/_utils/__init__.py
rai_agent_functions_api/_utils/serialization.py
rai_agent_functions_api/aio/__init__.py
rai_agent_functions_api/aio/_client.py
rai_agent_functions_api/aio/_configuration.py
rai_agent_functions_api/aio/_patch.py
rai_agent_functions_api/aio/operations/__init__.py
rai_agent_functions_api/aio/operations/_operations.py
rai_agent_functions_api/aio/operations/_patch.py
rai_agent_functions_api/operations/__init__.py
rai_agent_functions_api/operations/_operations.py
rai_agent_functions_api/operations/_patch.py
rai_agent_functions_api-1.0.3.dist-info/licenses/LICENSE
rai_agent_functions_api-1.0.3.dist-info/METADATA
rai_agent_functions_api-1.0.3.dist-info/WHEEL
rai_agent_functions_api-1.0.3.dist-info/top_level.txt
rai_agent_functions_api-1.0.3.dist-info/RECORD
