Metadata-Version: 2.4
Name: rai-agent-functions-api
Version: 1.0.3
Summary: Azure Functions API client for RAI (Responsible AI) operations including prompt review and testcase generation
Author-email: Divyanshu Rastogi <divyanshur@maqsoftware.com>
License-Expression: MIT
Project-URL: Homepage, https://github.com/DivyanshuMaq/rai-agent-functions-api
Project-URL: Documentation, https://github.com/DivyanshuMaq/rai-agent-functions-api#readme
Project-URL: Repository, https://github.com/DivyanshuMaq/rai-agent-functions-api.git
Project-URL: Bug Tracker, https://github.com/DivyanshuMaq/rai-agent-functions-api/issues
Keywords: azure,functions,api,responsible-ai,rai,prompt-review,testcase-generation
Classifier: Development Status :: 4 - Beta
Classifier: Intended Audience :: Developers
Classifier: Operating System :: OS Independent
Classifier: Programming Language :: Python :: 3
Classifier: Programming Language :: Python :: 3.8
Classifier: Programming Language :: Python :: 3.9
Classifier: Programming Language :: Python :: 3.10
Classifier: Programming Language :: Python :: 3.11
Classifier: Programming Language :: Python :: 3.12
Classifier: Topic :: Software Development :: Libraries :: Python Modules
Classifier: Topic :: Internet :: WWW/HTTP :: HTTP Servers
Requires-Python: >=3.8
License-File: LICENSE
Requires-Dist: azure-core>=1.24.0
Requires-Dist: typing-extensions>=4.0.0
Requires-Dist: isodate>=0.6.0
Provides-Extra: dev
Requires-Dist: pytest>=6.0; extra == "dev"
Requires-Dist: pytest-asyncio; extra == "dev"
Requires-Dist: black; extra == "dev"
Requires-Dist: flake8; extra == "dev"
Requires-Dist: mypy; extra == "dev"
Dynamic: license-file
